{
  "organization": "ADWISE",
  "idOrganization": 175,
  "date": "20/01/2022",
  "period": "Q4 2021",
  "summary": {
    "numSuscribers": 62,
    "percActivation": 83,
    "numSteps": 33044884.0,
    "numCalories": 188939.0,
    "bettercoins": 306989.0,
    "coverage": 30857143,
    "percBettercoins": 0.821,
    "numDonations": 831.0,
    "numCauses": 6,
    "message": " ¡Felicitaciones por haberse embarcado en este viaje de transformación e impacto! El bienestar de tus colaboradores y la protección financiera de sus seres queridos es el beneficio más grande que le puedes entregar.",
    "level": "SuperGiver",
    "perc_level": 6.0
  },
  "vision360": {
    "metrics": [
      "Porcentaje de enrolamiento",
      "Minutos de actividad física",
      "Bettercoins ganadas",
      "Minutos de meditación",
      "Cantidad de donaciones"
    ],
    "units": [
      "%",
      "minutos semanales por colaborador",
      "bettercoins semanales por colaborador",
      "minutos semanales por colaborador",
      "donaciones semanales por colaborador"
    ],
    "achievedValue": [
      52,
      22,
      182,
      0,
      0
    ],
    "sugestedValue": [
      62,
      180,
      420,
      10,
      1
    ],
    "achievedPercentage": [
      83,
      12,
      43,
      9,
      56
    ],
    "allOrganizations": [
      73,
      28,
      57,
      16,
      81
    ]
  },
  "impact": {
    "Agua": {
      "quantity": 170,
      "cause": [
        "Fight the water crisis"
      ],
      "idCause": [
        17
      ],
      "hasDonation": true
    },
    "Arboles": {
      "quantity": 193,
      "cause": [
        "Trees to save the future"
      ],
      "idCause": [
        18
      ],
      "hasDonation": true
    },
    "Comida": {
      "quantity": 384,
      "cause": [
        "Against child malnutrition in Haiti",
        "Chile's first food bank",
        "Feed a child in Venezuela"
      ],
      "idCause": [
        20,
        21,
        13
      ],
      "hasDonation": true
    }
  },
  "benefits": {
    "included": [
      {
        "nameBenefit": "Seguro de vida por fallecimiento natural",
        "idBenefit": 1,
        "isIncluded": true
      },
      {
        "nameBenefit": "Seguro de vida adicional fallecimiento accidental",
        "idBenefit": 2,
        "isIncluded": true
      },
      {
        "nameBenefit": "Seguro de invalidez accidental",
        "idBenefit": 3,
        "isIncluded": true
      },
      {
        "nameBenefit": "Atención médica en línea 24/7",
        "idBenefit": 4,
        "isIncluded": true
      },
      {
        "nameBenefit": "Consulta psicológica en línea",
        "idBenefit": 5,
        "isIncluded": true
      },
      {
        "nameBenefit": "Consulta nutricionista en línea",
        "idBenefit": 6,
        "isIncluded": false
      },
      {
        "nameBenefit": "Asesoría de ahorro e inversión",
        "idBenefit": 7,
        "isIncluded": true
      },
      {
        "nameBenefit": "Educación de bienestar",
        "idBenefit": 8,
        "isIncluded": true
      },
      {
        "nameBenefit": "Entrenamiento en casa",
        "idBenefit": 9,
        "isIncluded": true
      },
      {
        "nameBenefit": "Meditación y bienestar",
        "idBenefit": 10,
        "isIncluded": true
      }
    ],
    "activation": [
      {
        "partner": "Vida Security",
        "isIncluded": true,
        "percentage": 100,
        "idPartner": 1
      },
      {
        "partner": "Teledoc",
        "isIncluded": true,
        "percentage": 100,
        "idPartner": 2
      },
      {
        "partner": "The Big Know",
        "isIncluded": true,
        "percentage": 25,
        "idPartner": 6
      },
      {
        "partner": "Instafit",
        "isIncluded": true,
        "percentage": 17,
        "idPartner": 3
      },
      {
        "partner": "Puramente",
        "isIncluded": true,
        "percentage": 6,
        "idPartner": 4
      }
    ]
  },
  "activities": {
    "numSteps": 33044884.0,
    "message_year": "Tu organización ha recorrido el 62% de una vuelta al mundo. ¡Le faltan 14.888 kilómetros para dar una vuelta completa!",
    "best_month": {
      "month": "Diciembre",
      "steps": 5475235,
      "message": "Tu organización recorrió 3 veces el trayecto de Santiago a Buenos Aires este mes",
      "numActivities": 183,
      "meditationMin": 352,
      "numMeals": 71
    },
    "all_months": {
      "April": "6",
      "May": "50",
      "June": "78",
      "July": "59",
      "August": "125",
      "September": "81",
      "October": "103",
      "November": "121",
      "December": "208"
    }
  },
  "teleton": {
    "num_donations": "84",
    "bettercoins": "25200"
  },
  "bettertogether": {
    "total": 44,
    "clusters": [
      {
        "labels": "Principiantes",
        "pk_dim_organization": 175,
        "freq": 33,
        "perc": 75.0
      },
      {
        "labels": "Caminantes",
        "pk_dim_organization": 175,
        "freq": 6,
        "perc": 14.0
      },
      {
        "labels": "Amateurs",
        "pk_dim_organization": 175,
        "freq": 5,
        "perc": 11.0
      }
    ]
  }
}