{
  "organization": "Rubén Martínez",
  "idOrganization": 895,
  "date": "27/04/2022",
  "period": "Q4 2021",
  "summary": {
    "numSuscribers": 360,
    "percActivation": 11,
    "numSteps": 3973647.0,
    "numCalories": 2767.0,
    "bettercoins": 41850.0,
    "coverage": 4917206,
    "percBettercoins": 0.602,
    "numDonations": 84.0,
    "numCauses": 6,
    "message": " ¡Felicitaciones por haberse embarcado en este viaje de transformación e impacto! El bienestar de tus colaboradores y la protección financiera de sus seres queridos es el beneficio más grande que le puedes entregar.",
    "level": "Rookie",
    "perc_level": 97.0
  },
  "vision360": {
    "metrics": [
      "Porcentaje de enrolamiento",
      "Minutos de actividad física",
      "Bettercoins ganadas",
      "Minutos de meditación",
      "Cantidad de donaciones"
    ],
    "units": [
      "%",
      "minutos semanales por colaborador",
      "bettercoins semanales por colaborador",
      "minutos semanales por colaborador",
      "donaciones semanales por colaborador"
    ],
    "achievedValue": [
      40,
      2,
      113,
      0,
      0
    ],
    "sugestedValue": [
      360,
      180,
      420,
      10,
      1
    ],
    "achievedPercentage": [
      11,
      1,
      33,
      0,
      40
    ],
    "allOrganizations": [
      72,
      18,
      63,
      11,
      65
    ]
  },
  "impact": {
    "Agua": {
      "quantity": 35,
      "cause": [
        "Fight the water crisis"
      ],
      "idCause": [
        17
      ],
      "hasDonation": true
    },
    "Arboles": {
      "quantity": 14,
      "cause": [
        "Trees to save the future"
      ],
      "idCause": [
        18
      ],
      "hasDonation": true
    },
    "Comida": {
      "quantity": 34,
      "cause": [
        "Feed a child in Venezuela",
        "Against child malnutrition in Haiti",
        "Chile's first food bank"
      ],
      "idCause": [
        13,
        20,
        21
      ],
      "hasDonation": true
    },
    "Ucrania": {
      "quantity": 1,
      "cause": [
        "Let's support Ukraine"
      ],
      "idCause": [
        33
      ],
      "hasDonation": true
    },
    "Generic": {
      "quantity": 0,
      "cause": [],
      "idCause": [],
      "hasDonation": false
    }
  },
  "benefits": {
    "included": [
      {
        "nameBenefit": "Seguro de vida por fallecimiento natural",
        "idBenefit": 1,
        "isIncluded": true
      },
      {
        "nameBenefit": "Seguro de vida adicional fallecimiento accidental",
        "idBenefit": 2,
        "isIncluded": true
      },
      {
        "nameBenefit": "Seguro de invalidez accidental",
        "idBenefit": 3,
        "isIncluded": true
      },
      {
        "nameBenefit": "Atención médica en línea 24/7",
        "idBenefit": 4,
        "isIncluded": true
      },
      {
        "nameBenefit": "Consulta psicológica en línea",
        "idBenefit": 5,
        "isIncluded": true
      },
      {
        "nameBenefit": "Consulta nutricionista en línea",
        "idBenefit": 6,
        "isIncluded": true
      },
      {
        "nameBenefit": "Asesoría de ahorro e inversión",
        "idBenefit": 7,
        "isIncluded": true
      },
      {
        "nameBenefit": "Educación de bienestar",
        "idBenefit": 8,
        "isIncluded": false
      },
      {
        "nameBenefit": "Entrenamiento en casa",
        "idBenefit": 9,
        "isIncluded": false
      },
      {
        "nameBenefit": "Meditación y bienestar",
        "idBenefit": 10,
        "isIncluded": true
      }
    ]
  },
  "activities": {
    "numSteps": 2649,
    "message_year": "Tu organización ha recorrido el 88% del camino entre Santiago y Río de Janeiro. ¡Le faltan 350 kilómetros para llegar!",
    "donations": "34",
    "min_meditation": 0.0,
    "routine_activity": "36"
  },
  "manual_habits": 6,
  "bettertogether": {
    "total": 12,
    "clusters": [
      {
        "labels": "Principiantes",
        "pk_dim_organization": 895,
        "freq": 6,
        "perc": 50.0
      },
      {
        "labels": "Caminantes",
        "pk_dim_organization": 895,
        "freq": 6,
        "perc": 50.0
      }
    ]
  }
}